odoo8_addon_account_invoice_ubl-8.0.1.1.2-nspkg.pth
odoo_addons/account_invoice_ubl/README.rst
odoo_addons/account_invoice_ubl/__init__.py
odoo_addons/account_invoice_ubl/__openerp__.py
odoo_addons/account_invoice_ubl/i18n/account_invoice_ubl.pot
odoo_addons/account_invoice_ubl/i18n/fr.po
odoo_addons/account_invoice_ubl/i18n/pt_BR.po
odoo_addons/account_invoice_ubl/models/__init__.py
odoo_addons/account_invoice_ubl/models/account_invoice.py
odoo_addons/account_invoice_ubl/models/company.py
odoo_addons/account_invoice_ubl/models/report.py
odoo_addons/account_invoice_ubl/static/description/icon.png
odoo_addons/account_invoice_ubl/tests/__init__.py
odoo_addons/account_invoice_ubl/tests/test_ubl_generate.py
odoo_addons/account_invoice_ubl/views/account_invoice.xml
odoo_addons/account_invoice_ubl/views/company.xml
odoo8_addon_account_invoice_ubl-8.0.1.1.2.dist-info/METADATA
odoo8_addon_account_invoice_ubl-8.0.1.1.2.dist-info/WHEEL
odoo8_addon_account_invoice_ubl-8.0.1.1.2.dist-info/namespace_packages.txt
odoo8_addon_account_invoice_ubl-8.0.1.1.2.dist-info/top_level.txt
odoo8_addon_account_invoice_ubl-8.0.1.1.2.dist-info/RECORD
